culturekit/__init__.py
culturekit/__main__.py
culturekit/cleaning.py
culturekit/cli.py
culturekit/dataset.py
culturekit/evaluation.py
culturekit/models.py
culturekit/prompt_templates.py
culturekit/scoring.py
culturekit-0.0.2.dist-info/METADATA
culturekit-0.0.2.dist-info/WHEEL
culturekit-0.0.2.dist-info/entry_points.txt
culturekit-0.0.2.dist-info/licenses/LICENSE
culturekit-0.0.2.dist-info/RECORD
