Metadata-Version: 2.4
Name: culturekit
Version: 0.0.2
Summary: A toolkit for evaluating the culture of MLX large language models (LLMs) on the CD Eval benchmark.
Project-URL: repository, https://github.com/decisions-lab/culturekit
Project-URL: homepage, https://github.com/decisions-lab/culturekit
Project-URL: documentation, https://github.com/decisions-lab/culturekit
Author-email: devanshg03 <devansh@decisionslab.io>
License: MIT
License-File: LICENSE
Keywords: cultural-bias,evaluation,llm,machine-learning,mlx
Classifier: Development Status :: 3 - Alpha
Classifier: Intended Audience :: Science/Research
Classifier: License :: OSI Approved :: MIT License
Classifier: Programming Language :: Python :: 3
Classifier: Programming Language :: Python :: 3.11
Classifier: Topic :: Scientific/Engineering :: Artificial Intelligence
Requires-Python: >=3.11
Requires-Dist: azure-ai-inference>=1.0.0b8
Requires-Dist: azure-ai-ml>=1.24.0
Requires-Dist: azure-identity>=1.19.0
Requires-Dist: datasets>=3.2.0
Requires-Dist: ipywidgets>=8.1.5
Requires-Dist: jupyter>=1.1.1
Requires-Dist: langchain-openai>=0.3.13
Requires-Dist: matplotlib>=3.10.0
Requires-Dist: mlx-lm>=0.21.5
Requires-Dist: mlx>=0.22.0
Requires-Dist: numpy<2.0.0
Requires-Dist: pytest>=8.3.5
Requires-Dist: python-dotenv>=1.0.1
Requires-Dist: seaborn>=0.13.2
Requires-Dist: tensorflow>=2.18.0
Requires-Dist: torch>=2.5.1
Requires-Dist: tqdm>=4.67.1
Requires-Dist: typer>=0.15.2
Provides-Extra: dev
Requires-Dist: black>=24.2.0; extra == 'dev'
Requires-Dist: flake8>=7.0.0; extra == 'dev'
Requires-Dist: ipykernel>=6.29.5; extra == 'dev'
Requires-Dist: isort>=5.13.2; extra == 'dev'
Requires-Dist: mypy>=1.8.0; extra == 'dev'
Requires-Dist: pytest-cov>=4.1.0; extra == 'dev'
Requires-Dist: pytest>=8.0.0; extra == 'dev'
